{
  "steam_app_id": 1697540,
  "name": "AFTERGLOW",
  "slug": "afterglow",
  "developer": "DIRECTOR'S CUT",
  "publisher": "",
  "release_date": "2022-10-11",
  "price_usd": 1.79,
  "genres": [
    "Action",
    "Adventure"
  ],
  "tags": [
    "Action",
    "Adventure"
  ],
  "platforms": [
    "windows"
  ],
  "short_description": "AFTERGLOW - is an adventure game set in the post-war nuclear winter of 2058, where energy, weapons, and mods are valued above all else.",
  "header_image_url": "https://shared.akamai.steamstatic.com/store_item_assets/steam/apps/1697540/header.jpg?t=1737973215",
  "screenshots": [],
  "rising_score": 0.0,
  "gem_score": 0.0,
  "hype_score": 0.0,
  "review_velocity_7d": 0.30000000000000004,
  "follower_velocity_7d": 0.0,
  "classification": "tracked",
  "review_count": 6,
  "review_positive": 4,
  "review_percentage": 66.7,
  "owner_estimate": 10000,
  "ccu_estimate": 0,
  "follower_count": 0,
  "median_playtime_minutes": 0,
  "history": [
    {
      "date": "2026-04-04",
      "review_count": 6,
      "review_percentage": 66.7,
      "ccu_estimate": 0,
      "follower_count": 0
    },
    {
      "date": "2026-04-11",
      "review_count": 6,
      "review_percentage": 66.7,
      "ccu_estimate": 0,
      "follower_count": 0
    }
  ]
}