{
  "steam_app_id": 2850490,
  "name": "Axyz",
  "slug": "axyz",
  "developer": "Space Lion Studios",
  "publisher": "Space Lion Studios",
  "release_date": "Mar 27, 2025",
  "price_usd": 7.19,
  "genres": [
    "Casual",
    "Indie"
  ],
  "tags": [
    "Casual",
    "Indie"
  ],
  "platforms": [
    "windows",
    "mac",
    "linux"
  ],
  "short_description": "Roll, flip gravity and bend perspective in Axyz. Use your environmental and spatial awareness to beat over 100 levels and soak in the vaporwave in this tribute to 90s puzzle games.",
  "header_image_url": "https://shared.akamai.steamstatic.com/store_item_assets/steam/apps/2850490/header.jpg?t=1774217429",
  "screenshots": [
    "https://shared.akamai.steamstatic.com/store_item_assets/steam/apps/2850490/2b01983d8d047fb3d395979bb2ddfe280a2b99af/ss_2b01983d8d047fb3d395979bb2ddfe280a2b99af.600x338.jpg?t=1774217429",
    "https://shared.akamai.steamstatic.com/store_item_assets/steam/apps/2850490/ss_12dd1ef7ed57fc4c3812d35c328252d53c09382f.600x338.jpg?t=1774217429",
    "https://shared.akamai.steamstatic.com/store_item_assets/steam/apps/2850490/59248051cea6a9d91bbf9510206e8d4dddd1a773/ss_59248051cea6a9d91bbf9510206e8d4dddd1a773.600x338.jpg?t=1774217429",
    "https://shared.akamai.steamstatic.com/store_item_assets/steam/apps/2850490/ss_5df5e567f809f308e0a3f6677a068b9deda75f83.600x338.jpg?t=1774217429",
    "https://shared.akamai.steamstatic.com/store_item_assets/steam/apps/2850490/df916057db176b844b355397cf6dba47e028875d/ss_df916057db176b844b355397cf6dba47e028875d.600x338.jpg?t=1774217429",
    "https://shared.akamai.steamstatic.com/store_item_assets/steam/apps/2850490/ss_ab0fb97f253edb0cc23a838f88eaecbdef72e4c3.600x338.jpg?t=1774217429",
    "https://shared.akamai.steamstatic.com/store_item_assets/steam/apps/2850490/ss_d2165303b14809cd9c9d4291e4a85263995b478c.600x338.jpg?t=1774217429"
  ],
  "detailed_description": "<h2 class=\"bb_tag\" ><span class=\"bb_img_ctn\"><img class=\"bb_img\" src=\"https://shared.akamai.steamstatic.com/store_item_assets/steam/apps/2850490/extras/8dea28846251f6a4e1aab165969cdcd0.avif?t=1774217429\" width=616 height=120 /></span></h2><h2 class=\"bb_tag\" >A perspective-shifting puzzle game</h2><p class=\"bb_paragraph\" >📼 Find the Keys</p><p class=\"bb_paragraph\" >📼 Collect the Tapes</p><p class=\"bb_paragraph\" >📼 Switch Gravity </p><p class=\"bb_paragraph\" >📼 Over 100 levels </p><p class=\"bb_paragraph\" ><span class=\"bb_img_ctn\"><video class=\"bb_img\" autoplay muted loop playsinline poster=\"https://shared.akamai.steamstatic.com/store_item_assets/steam/apps/2850490/extras/9efb5fcd6d96a9c3f0302dbd16adca46.poster.avif?t=1774217429\" width=800 height=450 ><source src=\"https://shared.akamai.steamstatic.com/store_item_assets/steam/apps/2850490/extras/9efb5fcd6d96a9c3f0302dbd16adca46.webm?t=1774217429\" type=\"video/webm; codecs=vp9\"><source src=\"https://shared.akamai.steamstatic.com/store_item_assets/steam/apps/2850490/extras/9efb5fcd6d96a9c3f0302dbd16adca46.mp4?t=1774217429\" type=\"video/mp4\"></video></span></p><p class=\"bb_paragraph\" >Axyz is a vaporwave-flavoured tribute to 90s cult classic <strong>Kula World</strong>. Use your environmental and spacial awareness to find the key, reach the exit and beat the level. Replay levels as many times as you want to collect everything and record your best time!</p><p class=\"bb_paragraph\" ></p><p class=\"bb_paragraph\" ><span class=\"bb_img_ctn\"><img class=\"bb_img\" src=\"https://shared.akamai.steamstatic.com/store_item_assets/steam/apps/2850490/extras/2d2d6a3fb2dbf58080453ae3bd551b05.avif?t=1774217429\" width=616 height=120 /></span></p><p class=\"bb_paragraph\" ><span class=\"bb_img_ctn\"><video class=\"bb_img\" autoplay muted loop playsinline poster=\"https://shared.akamai.steamstatic.com/store_item_assets/steam/apps/2850490/extras/0cb639a00528741323855a13e83de827.poster.avif?t=1774217429\" width=600 height=338 ><source src=\"https://shared.akamai.steamstatic.com/store_item_assets/steam/apps/2850490/extras/0cb639a00528741323855a13e83de827.webm?t=1774217429\" type=\"video/webm; codecs=vp9\"><source src=\"https://shared.akamai.steamstatic.com/store_item_assets/steam/apps/2850490/extras/0cb639a00528741323855a13e83de827.mp4?t=1774217429\" type=\"video/mp4\"></video></span></p><p class=\"bb_paragraph\" >Each level has 5 tapes to collect in any order, providing an optional challenge for those wishing to push themselves to the limits. Find as many as you can to unlock more levels that provide a greater challenge and reach for 100% completion. </p><p class=\"bb_paragraph\" ></p><p class=\"bb_paragraph\" ><span class=\"bb_img_ctn\"><img class=\"bb_img\" src=\"https://shared.akamai.steamstatic.com/store_item_assets/steam/apps/2850490/extras/aee37e7f182934992d8f5df31d706200.avif?t=1774217429\" width=616 height=120 /></span></p><h2 class=\"bb_tag\" ><span class=\"bb_img_ctn\"><video class=\"bb_img\" autoplay muted loop playsinline poster=\"https://shared.akamai.steamstatic.com/store_item_assets/steam/apps/2850490/extras/7bf61e944065dfe203eb6a186b3addd9.poster.avif?t=1774217429\" width=800 height=450 ><source src=\"https://shared.akamai.steamstatic.com/store_item_assets/steam/apps/2850490/extras/7bf61e944065dfe203eb6a186b3addd9.webm?t=1774217429\" type=\"video/webm; codecs=vp9\"><source src=\"https://shared.akamai.steamstatic.com/store_item_assets/steam/apps/2850490/extras/7bf61e944065dfe203eb6a186b3addd9.mp4?t=1774217429\" type=\"video/mp4\"></video></span></h2><p class=\"bb_paragraph\" >Some items can only be reached by switching gravity. Levels will often have multiple ways to beat it and switching gravity if often the key. </p><p class=\"bb_paragraph\" ></p><p class=\"bb_paragraph\" ><span class=\"bb_img_ctn\"><img class=\"bb_img\" src=\"https://shared.akamai.steamstatic.com/store_item_assets/steam/apps/2850490/extras/0cc87dbc5339309834e60701eea00177.avif?t=1774217429\" width=616 height=120 /></span></p><p class=\"bb_paragraph\" ><span class=\"bb_img_ctn\"><video class=\"bb_img\" autoplay muted loop playsinline poster=\"https://shared.akamai.steamstatic.com/store_item_assets/steam/apps/2850490/extras/b98a6b906ab3cb77e3a0d5c85a4660ee.poster.avif?t=1774217429\" width=800 height=450 ><source src=\"https://shared.akamai.steamstatic.com/store_item_assets/steam/apps/2850490/extras/b98a6b906ab3cb77e3a0d5c85a4660ee.webm?t=1774217429\" type=\"video/webm; codecs=vp9\"><source src=\"https://shared.akamai.steamstatic.com/store_item_assets/steam/apps/2850490/extras/b98a6b906ab3cb77e3a0d5c85a4660ee.mp4?t=1774217429\" type=\"video/mp4\"></video></span></p><p class=\"bb_paragraph\" >Play over 100 mind-bending levels across 8 worlds.</p><p class=\"bb_paragraph\" ></p><p class=\"bb_paragraph\" ><span class=\"bb_img_ctn\"><img class=\"bb_img\" src=\"https://shared.akamai.steamstatic.com/store_item_assets/steam/apps/2850490/extras/667f8b8cd402921ad9623c5ce88b9b0d.avif?t=1774217429\" width=616 height=120 /></span></p><p class=\"bb_paragraph\" >A mixtape soundtrack featuring Pizza Hotline, Major Axis, CAIMANS, and many more.  Encompassing Drum and Bass, Breakbeat, Synthwave, and more to create an energetic and dreamlike soundtrack.</p>",
  "about_the_game": "<h2 class=\"bb_tag\" ><span class=\"bb_img_ctn\"><img class=\"bb_img\" src=\"https://shared.akamai.steamstatic.com/store_item_assets/steam/apps/2850490/extras/8dea28846251f6a4e1aab165969cdcd0.avif?t=1774217429\" width=616 height=120 /></span></h2><h2 class=\"bb_tag\" >A perspective-shifting puzzle game</h2><p class=\"bb_paragraph\" >📼 Find the Keys</p><p class=\"bb_paragraph\" >📼 Collect the Tapes</p><p class=\"bb_paragraph\" >📼 Switch Gravity </p><p class=\"bb_paragraph\" >📼 Over 100 levels </p><p class=\"bb_paragraph\" ><span class=\"bb_img_ctn\"><video class=\"bb_img\" autoplay muted loop playsinline poster=\"https://shared.akamai.steamstatic.com/store_item_assets/steam/apps/2850490/extras/9efb5fcd6d96a9c3f0302dbd16adca46.poster.avif?t=1774217429\" width=800 height=450 ><source src=\"https://shared.akamai.steamstatic.com/store_item_assets/steam/apps/2850490/extras/9efb5fcd6d96a9c3f0302dbd16adca46.webm?t=1774217429\" type=\"video/webm; codecs=vp9\"><source src=\"https://shared.akamai.steamstatic.com/store_item_assets/steam/apps/2850490/extras/9efb5fcd6d96a9c3f0302dbd16adca46.mp4?t=1774217429\" type=\"video/mp4\"></video></span></p><p class=\"bb_paragraph\" >Axyz is a vaporwave-flavoured tribute to 90s cult classic <strong>Kula World</strong>. Use your environmental and spacial awareness to find the key, reach the exit and beat the level. Replay levels as many times as you want to collect everything and record your best time!</p><p class=\"bb_paragraph\" ></p><p class=\"bb_paragraph\" ><span class=\"bb_img_ctn\"><img class=\"bb_img\" src=\"https://shared.akamai.steamstatic.com/store_item_assets/steam/apps/2850490/extras/2d2d6a3fb2dbf58080453ae3bd551b05.avif?t=1774217429\" width=616 height=120 /></span></p><p class=\"bb_paragraph\" ><span class=\"bb_img_ctn\"><video class=\"bb_img\" autoplay muted loop playsinline poster=\"https://shared.akamai.steamstatic.com/store_item_assets/steam/apps/2850490/extras/0cb639a00528741323855a13e83de827.poster.avif?t=1774217429\" width=600 height=338 ><source src=\"https://shared.akamai.steamstatic.com/store_item_assets/steam/apps/2850490/extras/0cb639a00528741323855a13e83de827.webm?t=1774217429\" type=\"video/webm; codecs=vp9\"><source src=\"https://shared.akamai.steamstatic.com/store_item_assets/steam/apps/2850490/extras/0cb639a00528741323855a13e83de827.mp4?t=1774217429\" type=\"video/mp4\"></video></span></p><p class=\"bb_paragraph\" >Each level has 5 tapes to collect in any order, providing an optional challenge for those wishing to push themselves to the limits. Find as many as you can to unlock more levels that provide a greater challenge and reach for 100% completion. </p><p class=\"bb_paragraph\" ></p><p class=\"bb_paragraph\" ><span class=\"bb_img_ctn\"><img class=\"bb_img\" src=\"https://shared.akamai.steamstatic.com/store_item_assets/steam/apps/2850490/extras/aee37e7f182934992d8f5df31d706200.avif?t=1774217429\" width=616 height=120 /></span></p><h2 class=\"bb_tag\" ><span class=\"bb_img_ctn\"><video class=\"bb_img\" autoplay muted loop playsinline poster=\"https://shared.akamai.steamstatic.com/store_item_assets/steam/apps/2850490/extras/7bf61e944065dfe203eb6a186b3addd9.poster.avif?t=1774217429\" width=800 height=450 ><source src=\"https://shared.akamai.steamstatic.com/store_item_assets/steam/apps/2850490/extras/7bf61e944065dfe203eb6a186b3addd9.webm?t=1774217429\" type=\"video/webm; codecs=vp9\"><source src=\"https://shared.akamai.steamstatic.com/store_item_assets/steam/apps/2850490/extras/7bf61e944065dfe203eb6a186b3addd9.mp4?t=1774217429\" type=\"video/mp4\"></video></span></h2><p class=\"bb_paragraph\" >Some items can only be reached by switching gravity. Levels will often have multiple ways to beat it and switching gravity if often the key. </p><p class=\"bb_paragraph\" ></p><p class=\"bb_paragraph\" ><span class=\"bb_img_ctn\"><img class=\"bb_img\" src=\"https://shared.akamai.steamstatic.com/store_item_assets/steam/apps/2850490/extras/0cc87dbc5339309834e60701eea00177.avif?t=1774217429\" width=616 height=120 /></span></p><p class=\"bb_paragraph\" ><span class=\"bb_img_ctn\"><video class=\"bb_img\" autoplay muted loop playsinline poster=\"https://shared.akamai.steamstatic.com/store_item_assets/steam/apps/2850490/extras/b98a6b906ab3cb77e3a0d5c85a4660ee.poster.avif?t=1774217429\" width=800 height=450 ><source src=\"https://shared.akamai.steamstatic.com/store_item_assets/steam/apps/2850490/extras/b98a6b906ab3cb77e3a0d5c85a4660ee.webm?t=1774217429\" type=\"video/webm; codecs=vp9\"><source src=\"https://shared.akamai.steamstatic.com/store_item_assets/steam/apps/2850490/extras/b98a6b906ab3cb77e3a0d5c85a4660ee.mp4?t=1774217429\" type=\"video/mp4\"></video></span></p><p class=\"bb_paragraph\" >Play over 100 mind-bending levels across 8 worlds.</p><p class=\"bb_paragraph\" ></p><p class=\"bb_paragraph\" ><span class=\"bb_img_ctn\"><img class=\"bb_img\" src=\"https://shared.akamai.steamstatic.com/store_item_assets/steam/apps/2850490/extras/667f8b8cd402921ad9623c5ce88b9b0d.avif?t=1774217429\" width=616 height=120 /></span></p><p class=\"bb_paragraph\" >A mixtape soundtrack featuring Pizza Hotline, Major Axis, CAIMANS, and many more.  Encompassing Drum and Bass, Breakbeat, Synthwave, and more to create an energetic and dreamlike soundtrack.</p>",
  "supported_languages": "English, French, German, Spanish - Spain, Italian, Portuguese - Brazil, Romanian, Irish, Japanese",
  "metacritic_score": null,
  "metacritic_url": "",
  "categories": [
    "Single-player",
    "Steam Achievements",
    "Full controller support",
    "Family Sharing"
  ],
  "trailer_url": "",
  "total_recommendations": 108,
  "rising_score": 0.0029,
  "gem_score": 0.7305,
  "hype_score": 0.0,
  "review_velocity_7d": 47.0,
  "follower_velocity_7d": 0.0,
  "classification": "hidden_gem",
  "review_count": 115,
  "review_positive": 115,
  "review_percentage": 100.0,
  "owner_estimate": 0,
  "ccu_estimate": 0,
  "follower_count": 0,
  "median_playtime_minutes": 0,
  "gem_tier": "rising",
  "history": [
    {
      "date": "2026-03-21",
      "review_count": 68,
      "review_percentage": 100.0,
      "ccu_estimate": 0,
      "follower_count": 0
    },
    {
      "date": "2026-03-26",
      "review_count": 115,
      "review_percentage": 100.0,
      "ccu_estimate": 0,
      "follower_count": 0
    }
  ],
  "reviews": []
}