{
  "steam_app_id": 1297800,
  "name": "ChronoBreach Ultra",
  "slug": "chronobreach-ultra",
  "developer": "UpsilonGames",
  "publisher": "",
  "release_date": "2021-11-18",
  "price_usd": 2.99,
  "genres": [
    "Action",
    "Indie"
  ],
  "tags": [
    "Action",
    "Indie"
  ],
  "platforms": [
    "windows"
  ],
  "short_description": "Dash through dangerous levels, warp time, and blast enemies in this time-bending action platformer! Manipulate the crumbling dimension of time to escape a deadly factory. Use your wit, your laser weap",
  "header_image_url": "https://shared.akamai.steamstatic.com/store_item_assets/steam/apps/1297800/header.jpg?t=1637996626",
  "screenshots": [],
  "rising_score": 0.0,
  "gem_score": 0.0,
  "hype_score": 0.0,
  "review_velocity_7d": 1.85,
  "follower_velocity_7d": 0.0,
  "classification": "tracked",
  "review_count": 37,
  "review_positive": 0,
  "review_percentage": 83.8,
  "owner_estimate": 0,
  "ccu_estimate": 0,
  "follower_count": 0,
  "median_playtime_minutes": 0,
  "history": [
    {
      "date": "2026-04-04",
      "review_count": 37,
      "review_percentage": 83.8,
      "ccu_estimate": 0,
      "follower_count": 0
    }
  ]
}