{
  "steam_app_id": 692530,
  "name": "Community Garden",
  "slug": "community-garden",
  "developer": "Somnium Space Ltd.",
  "publisher": "Somnium Space Ltd.",
  "release_date": "Oct 10, 2017",
  "price_usd": 9.99,
  "genres": [
    "Indie",
    "Massively Multiplayer",
    "Simulation",
    "Early Access"
  ],
  "tags": [
    "Indie",
    "Massively Multiplayer",
    "Simulation",
    "Early Access"
  ],
  "platforms": [
    "windows"
  ],
  "short_description": "A VR city powered Improbable's SpatialOS.",
  "header_image_url": "https://shared.akamai.steamstatic.com/store_item_assets/steam/apps/692530/header.jpg?t=1542698614",
  "screenshots": [
    "https://shared.akamai.steamstatic.com/store_item_assets/steam/apps/692530/ss_77891d05b4dbd00d84d9bdc52abbe9a66d822d85.600x338.jpg?t=1542698614",
    "https://shared.akamai.steamstatic.com/store_item_assets/steam/apps/692530/ss_0f911986b73980624878515a9ec94328cd2a98f0.600x338.jpg?t=1542698614",
    "https://shared.akamai.steamstatic.com/store_item_assets/steam/apps/692530/ss_f3d4256e5826fd1f6f1fe1cdd0c4c8b009f4d599.600x338.jpg?t=1542698614",
    "https://shared.akamai.steamstatic.com/store_item_assets/steam/apps/692530/ss_70af18c2e7182348f4eb8deaef8514f513bc07b5.600x338.jpg?t=1542698614",
    "https://shared.akamai.steamstatic.com/store_item_assets/steam/apps/692530/ss_2d9d69a5ad3ea2c9803d534b6341ff5d3a328b05.600x338.jpg?t=1542698614",
    "https://shared.akamai.steamstatic.com/store_item_assets/steam/apps/692530/ss_0eb68df438967940b6ae694d81abd4a9020a2aae.600x338.jpg?t=1542698614",
    "https://shared.akamai.steamstatic.com/store_item_assets/steam/apps/692530/ss_c9c2907a5a2e99516d892aacaeeb8c0c5488b2cb.600x338.jpg?t=1542698614",
    "https://shared.akamai.steamstatic.com/store_item_assets/steam/apps/692530/ss_0ee61bcdb6fe6c007b9e1cf39d2de6277019470a.600x338.jpg?t=1542698614",
    "https://shared.akamai.steamstatic.com/store_item_assets/steam/apps/692530/ss_c1c49f57e9d9c0f5055b0d62af795fd50fbcf745.600x338.jpg?t=1542698614"
  ],
  "detailed_description": "Community Garden exists as a place for the VR community to escape from reality. Explore the city, plant a garden or throw some rocks in a pond or shoot some hoops. Do all this with other VR players from around the world. Get lost in a VR city that focuses on realism and immersion. Join the Community Garden today!<br />\r\n<br />\r\nPowered by Improbable's SpatialOS",
  "about_the_game": "Community Garden exists as a place for the VR community to escape from reality. Explore the city, plant a garden or throw some rocks in a pond or shoot some hoops. Do all this with other VR players from around the world. Get lost in a VR city that focuses on realism and immersion. Join the Community Garden today!<br />\r\n<br />\r\nPowered by Improbable's SpatialOS",
  "supported_languages": "English",
  "metacritic_score": null,
  "metacritic_url": "",
  "categories": [
    "Multi-player",
    "MMO",
    "PvP",
    "Online PvP",
    "Co-op",
    "Online Co-op",
    "Tracked Controller Support",
    "VR Only",
    "Family Sharing"
  ],
  "trailer_url": "",
  "total_recommendations": 0,
  "rising_score": 0.0,
  "gem_score": 0.0,
  "hype_score": 0.0,
  "review_velocity_7d": 0.0,
  "follower_velocity_7d": 0.0,
  "classification": "tracked",
  "review_count": 10,
  "review_positive": 2,
  "review_percentage": 20.0,
  "owner_estimate": 0,
  "ccu_estimate": 0,
  "follower_count": 0,
  "median_playtime_minutes": 0,
  "history": [
    {
      "date": "2026-03-21",
      "review_count": 11,
      "review_percentage": 18.2,
      "ccu_estimate": 0,
      "follower_count": 0
    },
    {
      "date": "2026-03-23",
      "review_count": 10,
      "review_percentage": 20.0,
      "ccu_estimate": 0,
      "follower_count": 0
    }
  ],
  "reviews": []
}