{
  "steam_app_id": 1545990,
  "name": "Deadeye Deepfake Simulacrum",
  "slug": "deadeye-deepfake-simulacrum",
  "developer": "nodayshalleraseyou",
  "publisher": "",
  "release_date": "2025-09-18",
  "price_usd": 9.74,
  "genres": [
    "Action",
    "Indie",
    "RPG",
    "Simulation"
  ],
  "tags": [
    "Action",
    "Indie",
    "RPG",
    "Simulation"
  ],
  "platforms": [
    "windows",
    "mac",
    "linux"
  ],
  "short_description": "Embody the ultimate cybernetic corporate agent. Master deadly gunplay, time manipulation, and supernatural abilities. Hack computers, people, even the individual bullets flying at you. Confront the fu",
  "header_image_url": "https://shared.akamai.steamstatic.com/store_item_assets/steam/apps/1545990/8d422f22ad9c7ef01746ec7ce1ed1aa9d569cb27/header.jpg?t=1758223099",
  "screenshots": [],
  "rising_score": 0.0002,
  "gem_score": 0.0,
  "hype_score": 0.0,
  "review_velocity_7d": 40.300000000000004,
  "follower_velocity_7d": 0.0,
  "classification": "tracked",
  "review_count": 806,
  "review_positive": 0,
  "review_percentage": 98.6,
  "owner_estimate": 0,
  "ccu_estimate": 0,
  "follower_count": 0,
  "median_playtime_minutes": 0,
  "history": [
    {
      "date": "2026-04-04",
      "review_count": 806,
      "review_percentage": 98.6,
      "ccu_estimate": 0,
      "follower_count": 0
    }
  ]
}