{
  "steam_app_id": 1426310,
  "name": "Dee-6: Dice Defenders",
  "slug": "dee-6-dice-defenders",
  "developer": "KBA3u's factory",
  "publisher": "",
  "release_date": "2021-03-31",
  "price_usd": 4.99,
  "genres": [
    "Indie",
    "Simulation",
    "Strategy"
  ],
  "tags": [
    "Indie",
    "Simulation",
    "Strategy"
  ],
  "platforms": [
    "windows"
  ],
  "short_description": "Dee-6: Dice Defenders is a game about survival in space travel, about the fight against internal and external threats, about the distribution of the power of the dice-team and, of course, about luck!",
  "header_image_url": "https://shared.akamai.steamstatic.com/store_item_assets/steam/apps/1426310/header.jpg?t=1680735680",
  "screenshots": [],
  "rising_score": 0.0,
  "gem_score": 0.0,
  "hype_score": 0.0,
  "review_velocity_7d": 2.45,
  "follower_velocity_7d": 0.0,
  "classification": "tracked",
  "review_count": 49,
  "review_positive": 0,
  "review_percentage": 75.5,
  "owner_estimate": 0,
  "ccu_estimate": 0,
  "follower_count": 0,
  "median_playtime_minutes": 0,
  "history": [
    {
      "date": "2026-04-04",
      "review_count": 49,
      "review_percentage": 75.5,
      "ccu_estimate": 0,
      "follower_count": 0
    }
  ]
}