{
  "steam_app_id": 1522140,
  "name": "Demon Skin",
  "slug": "demon-skin",
  "developer": "Ludus future",
  "publisher": "",
  "release_date": "2021-04-13",
  "price_usd": 2.49,
  "genres": [
    "Action",
    "Adventure",
    "Indie",
    "RPG"
  ],
  "tags": [
    "Action",
    "Adventure",
    "Indie",
    "RPG"
  ],
  "platforms": [
    "windows"
  ],
  "short_description": "Brutal Hack&Slash game with a challenging combat system plunges you into the harsh dark fantasy world to test your will and your skills. Only those who dare to get into the Demon Skin can survive!",
  "header_image_url": "https://shared.akamai.steamstatic.com/store_item_assets/steam/apps/1522140/header.jpg?t=1761209746",
  "screenshots": [],
  "rising_score": 0.0,
  "gem_score": 0.0,
  "hype_score": 0.0,
  "review_velocity_7d": 7.0,
  "follower_velocity_7d": 0.0,
  "classification": "tracked",
  "review_count": 140,
  "review_positive": 0,
  "review_percentage": 72.1,
  "owner_estimate": 0,
  "ccu_estimate": 0,
  "follower_count": 0,
  "median_playtime_minutes": 0,
  "history": [
    {
      "date": "2026-04-04",
      "review_count": 140,
      "review_percentage": 72.1,
      "ccu_estimate": 0,
      "follower_count": 0
    }
  ]
}