{
  "steam_app_id": 1365940,
  "name": "Eye of the Temple: First Steps",
  "slug": "eye-of-the-temple-first-steps",
  "developer": "Rune Skovbo Johansen",
  "publisher": "",
  "release_date": "2020-08-27",
  "price_usd": 0.0,
  "genres": [
    "Action",
    "Adventure",
    "Indie",
    "Free To Play"
  ],
  "tags": [
    "Action",
    "Adventure",
    "Indie",
    "Free To Play"
  ],
  "platforms": [
    "windows"
  ],
  "short_description": "This introduction to Eye of the Temple lets you step into a vast and treacherous temple in VR using your own feet. Keep your balance as you step from one moving block to another, dodging traps and sol",
  "header_image_url": "https://shared.akamai.steamstatic.com/store_item_assets/steam/apps/1365940/header.jpg?t=1726329324",
  "screenshots": [],
  "rising_score": 0.0001,
  "gem_score": 0.0,
  "hype_score": 0.0,
  "review_velocity_7d": 13.8,
  "follower_velocity_7d": 0.0,
  "classification": "tracked",
  "review_count": 276,
  "review_positive": 0,
  "review_percentage": 93.8,
  "owner_estimate": 0,
  "ccu_estimate": 0,
  "follower_count": 0,
  "median_playtime_minutes": 0,
  "history": [
    {
      "date": "2026-04-04",
      "review_count": 276,
      "review_percentage": 93.8,
      "ccu_estimate": 0,
      "follower_count": 0
    }
  ]
}