{
  "steam_app_id": 627220,
  "name": "Food Truck VR",
  "slug": "food-truck-vr",
  "developer": "Gambit Games Studio, LLC",
  "publisher": "Gambit Games Studio, LLC",
  "release_date": "Jul 12, 2018",
  "price_usd": 0.0,
  "genres": [
    "Casual",
    "Indie",
    "Simulation"
  ],
  "tags": [
    "Casual",
    "Indie",
    "Simulation"
  ],
  "platforms": [
    "windows"
  ],
  "short_description": "Food Truck VR is a Restaurant Simulator! Build up your menu, frantically serve up to 4 customers at a time, and cook on all manner of different equipment to craft your recipes! You, the player, will be graded on how well you cook!",
  "header_image_url": "https://shared.akamai.steamstatic.com/store_item_assets/steam/apps/627220/header.jpg?t=1642438389",
  "screenshots": [
    "https://shared.akamai.steamstatic.com/store_item_assets/steam/apps/627220/ss_e31e2a35220b6ad2435086534b4f72cce1056de2.600x338.jpg?t=1642438389",
    "https://shared.akamai.steamstatic.com/store_item_assets/steam/apps/627220/ss_411a8d5141a252f6d034d0aad2645b4375ef9272.600x338.jpg?t=1642438389",
    "https://shared.akamai.steamstatic.com/store_item_assets/steam/apps/627220/ss_b8daa2e97751b322bcafc020b61d1cc17f7f6573.600x338.jpg?t=1642438389",
    "https://shared.akamai.steamstatic.com/store_item_assets/steam/apps/627220/ss_7ed66b280484c0faab763c9edb39662eef5e04f0.600x338.jpg?t=1642438389",
    "https://shared.akamai.steamstatic.com/store_item_assets/steam/apps/627220/ss_124718f6a260bcb816fad30d57db88fff9eb2626.600x338.jpg?t=1642438389",
    "https://shared.akamai.steamstatic.com/store_item_assets/steam/apps/627220/ss_7d02c856b16406e921b665e7995dd4f4f2fa44b4.600x338.jpg?t=1642438389",
    "https://shared.akamai.steamstatic.com/store_item_assets/steam/apps/627220/ss_b06970e6199c694f65d0f40de3291db7b40f5963.600x338.jpg?t=1642438389",
    "https://shared.akamai.steamstatic.com/store_item_assets/steam/apps/627220/ss_2e1aee33e95ccf16fbf0f5dd1b3ef876aa8e744c.600x338.jpg?t=1642438389",
    "https://shared.akamai.steamstatic.com/store_item_assets/steam/apps/627220/ss_98eea9e9f09abe821e0eb7e97650f614fc03e148.600x338.jpg?t=1642438389"
  ],
  "detailed_description": "Food Truck VR is a virtual reality restaurant simulator that allows you to play both chef and entrepreneur! Build up your menu, prepare your recipes on all manner of cooking equipment, and frantically serve up to 4 customers at a time. You, the player, will be graded on how well you cook, and how quickly you serve dishes- the food critics can be especially demanding!<br />\r\n<br />\r\nCustomize your restaurant and serve the types of dishes you want, but remember to keep your customers happy, or they won't want to come back!",
  "about_the_game": "Food Truck VR is a virtual reality restaurant simulator that allows you to play both chef and entrepreneur! Build up your menu, prepare your recipes on all manner of cooking equipment, and frantically serve up to 4 customers at a time. You, the player, will be graded on how well you cook, and how quickly you serve dishes- the food critics can be especially demanding!<br />\r\n<br />\r\nCustomize your restaurant and serve the types of dishes you want, but remember to keep your customers happy, or they won't want to come back!",
  "supported_languages": "English<strong>*</strong><br><strong>*</strong>languages with full audio support",
  "metacritic_score": null,
  "metacritic_url": "",
  "categories": [
    "Single-player",
    "Steam Achievements",
    "VR Only",
    "Steam Trading Cards",
    "Family Sharing"
  ],
  "trailer_url": "",
  "total_recommendations": 0,
  "rising_score": 0.0,
  "gem_score": 0.0,
  "hype_score": 0.0,
  "review_velocity_7d": 0.0,
  "follower_velocity_7d": 0.0,
  "classification": "tracked",
  "review_count": 19,
  "review_positive": 14,
  "review_percentage": 73.7,
  "owner_estimate": 0,
  "ccu_estimate": 0,
  "follower_count": 0,
  "median_playtime_minutes": 0,
  "history": [
    {
      "date": "2026-03-21",
      "review_count": 19,
      "review_percentage": 73.7,
      "ccu_estimate": 0,
      "follower_count": 0
    },
    {
      "date": "2026-03-23",
      "review_count": 19,
      "review_percentage": 73.7,
      "ccu_estimate": 0,
      "follower_count": 0
    }
  ],
  "reviews": []
}