{
  "steam_app_id": 2516980,
  "name": "Heroes & Redemption",
  "slug": "heroes-redemption",
  "developer": "Observer Games",
  "publisher": "",
  "release_date": "2024-11-18",
  "price_usd": 0.0,
  "genres": [
    "Action",
    "Indie",
    "RPG",
    "Free To Play"
  ],
  "tags": [
    "Action",
    "Indie",
    "RPG",
    "Free To Play"
  ],
  "platforms": [
    "windows",
    "linux"
  ],
  "short_description": "Heroes & Redemption is a rogue-lite bullet-hell where you face hordes of enemies, annihilate them, learn new abilities and enhance your skills. Explore different regions, acquire new companions an",
  "header_image_url": "https://shared.akamai.steamstatic.com/store_item_assets/steam/apps/2516980/header.jpg?t=1748603979",
  "screenshots": [],
  "rising_score": 0.0,
  "gem_score": 0.0,
  "hype_score": 0.0,
  "review_velocity_7d": 3.85,
  "follower_velocity_7d": 0.0,
  "classification": "tracked",
  "review_count": 77,
  "review_positive": 0,
  "review_percentage": 84.4,
  "owner_estimate": 0,
  "ccu_estimate": 0,
  "follower_count": 0,
  "median_playtime_minutes": 0,
  "history": [
    {
      "date": "2026-04-04",
      "review_count": 77,
      "review_percentage": 84.4,
      "ccu_estimate": 0,
      "follower_count": 0
    }
  ]
}