{
  "steam_app_id": 1065770,
  "name": "Home A Drone",
  "slug": "home-a-drone",
  "developer": "Construct Studio",
  "publisher": "",
  "release_date": "2019-09-19",
  "price_usd": 9.99,
  "genres": [
    "Action",
    "Casual",
    "Indie",
    "Strategy",
    "Early Access"
  ],
  "tags": [
    "Action",
    "Casual",
    "Indie",
    "Strategy",
    "Early Access"
  ],
  "platforms": [
    "windows"
  ],
  "short_description": "My Pa said the world would go to hell once Artificially Intelligent drones took over. I don’t much care what they do, as long as they stay off my damn lawn and out of my business!",
  "header_image_url": "https://shared.akamai.steamstatic.com/store_item_assets/steam/apps/1065770/header.jpg?t=1574707830",
  "screenshots": [],
  "rising_score": 0.0,
  "gem_score": 0.0,
  "hype_score": 0.0,
  "review_velocity_7d": 0.35000000000000003,
  "follower_velocity_7d": 0.0,
  "classification": "tracked",
  "review_count": 7,
  "review_positive": 0,
  "review_percentage": 85.7,
  "owner_estimate": 0,
  "ccu_estimate": 0,
  "follower_count": 0,
  "median_playtime_minutes": 0,
  "history": [
    {
      "date": "2026-04-04",
      "review_count": 7,
      "review_percentage": 85.7,
      "ccu_estimate": 0,
      "follower_count": 0
    }
  ]
}