{
  "steam_app_id": 1346830,
  "name": "I Saw Black Clouds",
  "slug": "i-saw-black-clouds",
  "developer": "Ghost Dog Films",
  "publisher": "",
  "release_date": "2021-03-30",
  "price_usd": 2.54,
  "genres": [
    "Adventure"
  ],
  "tags": [
    "Adventure"
  ],
  "platforms": [
    "windows",
    "mac"
  ],
  "short_description": "After the unexpected death of a close friend, Kristina returns to her hometown looking for answers, only to unearth a string of dark secrets. I Saw Black Clouds is an interactive psychological thrille",
  "header_image_url": "https://shared.akamai.steamstatic.com/store_item_assets/steam/apps/1346830/header.jpg?t=1727963871",
  "screenshots": [],
  "rising_score": 0.0001,
  "gem_score": 0.0,
  "hype_score": 0.0,
  "review_velocity_7d": 31.6,
  "follower_velocity_7d": 0.0,
  "classification": "tracked",
  "review_count": 632,
  "review_positive": 0,
  "review_percentage": 61.6,
  "owner_estimate": 0,
  "ccu_estimate": 0,
  "follower_count": 0,
  "median_playtime_minutes": 0,
  "history": [
    {
      "date": "2026-04-04",
      "review_count": 632,
      "review_percentage": 61.6,
      "ccu_estimate": 0,
      "follower_count": 0
    }
  ]
}