{
  "steam_app_id": 948340,
  "name": "Journey Through Memories",
  "slug": "journey-through-memories",
  "developer": "Niken Hertanto, Inkan Hertanto, Juan Rosales, Runze (Eric) Guo, Patrick Kagel",
  "publisher": "",
  "release_date": "2018-10-20",
  "price_usd": 0.99,
  "genres": [
    "Indie"
  ],
  "tags": [
    "Indie"
  ],
  "platforms": [
    "windows"
  ],
  "short_description": "Use your voice to guide a young witch named Vivi as she travels through a hand painted, 2D world plagued by a devastating war. Discover spells, cast powerful magic, find missing memoirs, and help ling",
  "header_image_url": "https://shared.akamai.steamstatic.com/store_item_assets/steam/apps/948340/header.jpg?t=1540059757",
  "screenshots": [],
  "review_count": 6,
  "review_positive": 0,
  "review_percentage": 83.3,
  "owner_estimate": 0,
  "ccu_estimate": 0,
  "follower_count": 0,
  "median_playtime_minutes": 0,
  "history": [
    {
      "date": "2026-04-04",
      "review_count": 6,
      "review_percentage": 83.3,
      "ccu_estimate": 0,
      "follower_count": 0
    }
  ]
}