{
  "steam_app_id": 1462430,
  "name": "Ms.Director",
  "slug": "msdirector",
  "developer": "SketchyNonsense",
  "publisher": "",
  "release_date": "2021-05-17",
  "price_usd": 0.0,
  "genres": [
    "Adventure",
    "Indie",
    "Free To Play"
  ],
  "tags": [
    "Adventure",
    "Indie",
    "Free To Play"
  ],
  "platforms": [
    "windows"
  ],
  "short_description": "Cameras and heads are rolling in this noir inspired RPGmaker horror game. Save the spectral starlets trapped in the deadly director's mansion, and escape without joining them in their fate.",
  "header_image_url": "https://shared.akamai.steamstatic.com/store_item_assets/steam/apps/1462430/header.jpg?t=1731516295",
  "screenshots": [],
  "rising_score": 0.0006,
  "gem_score": 0.788,
  "hype_score": 0.0,
  "review_velocity_7d": 0.0,
  "follower_velocity_7d": 0.0,
  "classification": "new_release",
  "review_count": 67,
  "review_positive": 0,
  "review_percentage": 97.0,
  "owner_estimate": 0,
  "ccu_estimate": 0,
  "follower_count": 0,
  "median_playtime_minutes": 0,
  "history": [
    {
      "date": "2026-04-04",
      "review_count": 67,
      "review_percentage": 97.0,
      "ccu_estimate": 0,
      "follower_count": 0
    }
  ]
}