{
  "steam_app_id": 384490,
  "name": "NECROPOLIS: BRUTAL EDITION",
  "slug": "necropolis-brutal-edition",
  "developer": "Harebrained Schemes",
  "publisher": "",
  "release_date": "2016-07-12",
  "price_usd": 7.49,
  "genres": [
    "Action",
    "Adventure",
    "Indie"
  ],
  "tags": [
    "Action",
    "Adventure",
    "Indie"
  ],
  "platforms": [
    "windows",
    "mac"
  ],
  "short_description": "NECROPOLIS: BRUTAL EDITION is a major update featuring a new playable adventurer (The Brute), a completely new outdoor environment (The Black Forest), and lots of new enemies, weapons, armor, traps, p",
  "header_image_url": "https://shared.akamai.steamstatic.com/store_item_assets/steam/apps/384490/header.jpg?t=1711112928",
  "screenshots": [],
  "review_count": 4648,
  "review_positive": 0,
  "review_percentage": 64.9,
  "owner_estimate": 350000,
  "ccu_estimate": 0,
  "follower_count": 0,
  "median_playtime_minutes": 0,
  "history": [
    {
      "date": "2026-04-04",
      "review_count": 4648,
      "review_percentage": 64.9,
      "ccu_estimate": 0,
      "follower_count": 0
    }
  ]
}