{
  "steam_app_id": 2855660,
  "name": "NewMe NuMe LuMe: Alien Wars",
  "slug": "newme-nume-lume-alien-wars",
  "developer": "Ho RaBii",
  "publisher": "",
  "release_date": "2024-04-12",
  "price_usd": 1.19,
  "genres": [
    "Action",
    "Casual",
    "Indie"
  ],
  "tags": [
    "Action",
    "Casual",
    "Indie"
  ],
  "platforms": [
    "windows"
  ],
  "short_description": "Summoned into the otherworldly realm of 'NewMe NuMe LuMe', the protagonist Kim Ttolttol must aid the gods who summoned her to defeat enemies and return home in this 2D top-down action game. Utilize a ",
  "header_image_url": "https://shared.akamai.steamstatic.com/store_item_assets/steam/apps/2855660/96ddbcc25ddb4f097d25153b07112094b7ebd641/header.jpg?t=1764262169",
  "screenshots": [],
  "review_count": 6,
  "review_positive": 0,
  "review_percentage": 100.0,
  "owner_estimate": 0,
  "ccu_estimate": 0,
  "follower_count": 0,
  "median_playtime_minutes": 0,
  "history": [
    {
      "date": "2026-04-04",
      "review_count": 6,
      "review_percentage": 100.0,
      "ccu_estimate": 0,
      "follower_count": 0
    }
  ]
}