{
  "steam_app_id": 791260,
  "name": "Pandora: Chains of Chaos",
  "slug": "pandora-chains-of-chaos",
  "developer": "Party Llama Games",
  "publisher": "",
  "release_date": "2020-09-22",
  "price_usd": 0.99,
  "genres": [
    "Action",
    "Adventure",
    "Early Access"
  ],
  "tags": [
    "Action",
    "Adventure",
    "Early Access"
  ],
  "platforms": [
    "windows"
  ],
  "short_description": "A 17-year-old girl named Pandora has opened a box containing evils that could destroy the world. Kome Village, her home, is invaded by creatures spawned from the darkness and the legendary Titans. Dur",
  "header_image_url": "https://shared.akamai.steamstatic.com/store_item_assets/steam/apps/791260/header.jpg?t=1748532092",
  "screenshots": [],
  "review_count": 20,
  "review_positive": 0,
  "review_percentage": 50.0,
  "owner_estimate": 10000,
  "ccu_estimate": 0,
  "follower_count": 0,
  "median_playtime_minutes": 0,
  "history": [
    {
      "date": "2026-04-04",
      "review_count": 20,
      "review_percentage": 50.0,
      "ccu_estimate": 0,
      "follower_count": 0
    }
  ]
}