{
  "steam_app_id": 2429930,
  "name": "Power Network Tycoon",
  "slug": "power-network-tycoon",
  "developer": "David Made This",
  "publisher": "",
  "release_date": "2024-02-12",
  "price_usd": 11.99,
  "genres": [
    "Indie",
    "Simulation",
    "Strategy",
    "Early Access"
  ],
  "tags": [
    "Indie",
    "Simulation",
    "Strategy",
    "Early Access"
  ],
  "platforms": [
    "windows",
    "mac",
    "linux"
  ],
  "short_description": "Power Network Tycoon is a power grid simulation and strategy game where you build and maintain high-voltage power networks. Construct infrastructure, monitor resources, research upgrades, adapt to env",
  "header_image_url": "https://shared.akamai.steamstatic.com/store_item_assets/steam/apps/2429930/header.jpg?t=1772746429",
  "screenshots": [],
  "rising_score": 0.0,
  "gem_score": 0.0,
  "hype_score": 0.0,
  "review_velocity_7d": 1.4000000000000001,
  "follower_velocity_7d": 0.0,
  "classification": "tracked",
  "review_count": 28,
  "review_positive": 0,
  "review_percentage": 96.4,
  "owner_estimate": 0,
  "ccu_estimate": 0,
  "follower_count": 0,
  "median_playtime_minutes": 0,
  "history": [
    {
      "date": "2026-04-04",
      "review_count": 28,
      "review_percentage": 96.4,
      "ccu_estimate": 0,
      "follower_count": 0
    }
  ]
}