{
  "steam_app_id": 2267860,
  "name": "Project X",
  "slug": "project-x",
  "developer": "Marco Games",
  "publisher": "Hoi 4 Deu",
  "release_date": "May 4, 2023",
  "price_usd": 1.99,
  "genres": [
    "Action",
    "Adventure",
    "Indie",
    "RPG"
  ],
  "tags": [
    "Action",
    "Adventure",
    "Indie",
    "RPG"
  ],
  "platforms": [
    "windows"
  ],
  "short_description": "Project X is a funny little rpg zombie shooter, but no regular rpg maker game. The usual battle scenes are not used, you have to shoot the zombies with guns. This game is made for you if you like rpg maker games made different than they should. There is no real story, it's just a little fun game.",
  "header_image_url": "https://shared.akamai.steamstatic.com/store_item_assets/steam/apps/2267860/header.jpg?t=1733048500",
  "screenshots": [
    "https://shared.akamai.steamstatic.com/store_item_assets/steam/apps/2267860/ss_2a3d610ac3aa4b45c1e558b53b924a30b3c0a258.600x338.jpg?t=1733048500",
    "https://shared.akamai.steamstatic.com/store_item_assets/steam/apps/2267860/ss_bbdaf8b316ca644ed61f837d3808595b1cb7aa62.600x338.jpg?t=1733048500",
    "https://shared.akamai.steamstatic.com/store_item_assets/steam/apps/2267860/ss_70662550a4de8fb3aed10c3aa80f8faa721cdd4b.600x338.jpg?t=1733048500",
    "https://shared.akamai.steamstatic.com/store_item_assets/steam/apps/2267860/ss_ca9666783369e612ce6d08430046fcac6312e543.600x338.jpg?t=1733048500",
    "https://shared.akamai.steamstatic.com/store_item_assets/steam/apps/2267860/ss_f4bc2f972e6d94aac08ddca38709f04ab3922663.600x338.jpg?t=1733048500",
    "https://shared.akamai.steamstatic.com/store_item_assets/steam/apps/2267860/ss_6858c412e0acb69a8e9dd70ae5577c890ccf7725.600x338.jpg?t=1733048500",
    "https://shared.akamai.steamstatic.com/store_item_assets/steam/apps/2267860/ss_c515a3f5b1538c481835237785693be372686e04.600x338.jpg?t=1733048500",
    "https://shared.akamai.steamstatic.com/store_item_assets/steam/apps/2267860/ss_3a4b2b3a1bcb62cafd0bc9489d79dcb511a14bbc.600x338.jpg?t=1733048500",
    "https://shared.akamai.steamstatic.com/store_item_assets/steam/apps/2267860/ss_9e4b2a485c8792dd8083d2ce672f18f0ca698e77.600x338.jpg?t=1733048500",
    "https://shared.akamai.steamstatic.com/store_item_assets/steam/apps/2267860/ss_250d30c93dabd9235ecc0824aacb9af50a3dd5b0.600x338.jpg?t=1733048500",
    "https://shared.akamai.steamstatic.com/store_item_assets/steam/apps/2267860/ss_ff69edf79eb02b84fa594e7add07c8a4f32ddfc9.600x338.jpg?t=1733048500",
    "https://shared.akamai.steamstatic.com/store_item_assets/steam/apps/2267860/ss_8de757edfcf05cf15b953634c7950b496e69a86f.600x338.jpg?t=1733048500"
  ],
  "detailed_description": "Project X is a funny little rpg zombie shooter, but no regular rpg maker game. The usual battle scenes are not used, you have to shoot the zombies with guns. This game is made for you if you like rpg maker games made different than they should. There is no real story, it's just a little fun game.<br />\r\n<br />\r\nThere is a zombie apocalypse and you have to go on a journey to stop it. By shooting zombies you'll earn money that you can use to buy weapons such as machine guns. The zombies get stronger and stronger the further you get on the journey.",
  "about_the_game": "Project X is a funny little rpg zombie shooter, but no regular rpg maker game. The usual battle scenes are not used, you have to shoot the zombies with guns. This game is made for you if you like rpg maker games made different than they should. There is no real story, it's just a little fun game.<br />\r\n<br />\r\nThere is a zombie apocalypse and you have to go on a journey to stop it. By shooting zombies you'll earn money that you can use to buy weapons such as machine guns. The zombies get stronger and stronger the further you get on the journey.",
  "supported_languages": "English, German, Spanish - Spain, Simplified Chinese, Japanese",
  "metacritic_score": null,
  "metacritic_url": "",
  "categories": [
    "Single-player",
    "Steam Cloud",
    "Family Sharing"
  ],
  "trailer_url": "",
  "total_recommendations": 0,
  "rising_score": 0.0,
  "gem_score": 0.0,
  "hype_score": 0.0,
  "review_velocity_7d": 1.0,
  "follower_velocity_7d": 0.0,
  "classification": "tracked",
  "review_count": 2,
  "review_positive": 1,
  "review_percentage": 50.0,
  "owner_estimate": 0,
  "ccu_estimate": 0,
  "follower_count": 0,
  "median_playtime_minutes": 0,
  "history": [
    {
      "date": "2026-03-21",
      "review_count": 1,
      "review_percentage": 0.0,
      "ccu_estimate": 0,
      "follower_count": 0
    },
    {
      "date": "2026-03-25",
      "review_count": 2,
      "review_percentage": 50.0,
      "ccu_estimate": 0,
      "follower_count": 0
    }
  ],
  "reviews": []
}