{
  "steam_app_id": 907780,
  "name": "Puzzle Noid",
  "slug": "puzzle-noid",
  "developer": "Red13Indie",
  "publisher": "",
  "release_date": "2018-08-11",
  "price_usd": 1.19,
  "genres": [
    "Casual",
    "Indie"
  ],
  "tags": [
    "Casual",
    "Indie"
  ],
  "platforms": [
    "windows"
  ],
  "short_description": "Puzzle Noid challenges you in 10 different levels to breaking through the prejudices imposed by society. Differently of other games of its gender, Puzzle Noid develops the player perception making you",
  "header_image_url": "https://shared.akamai.steamstatic.com/store_item_assets/steam/apps/907780/header.jpg?t=1679691235",
  "screenshots": [],
  "review_count": 1,
  "review_positive": 0,
  "review_percentage": 100.0,
  "owner_estimate": 0,
  "ccu_estimate": 0,
  "follower_count": 0,
  "median_playtime_minutes": 0,
  "history": [
    {
      "date": "2026-04-04",
      "review_count": 1,
      "review_percentage": 100.0,
      "ccu_estimate": 0,
      "follower_count": 0
    }
  ]
}