{
  "steam_app_id": 794300,
  "name": "Simple Man",
  "slug": "simple-man",
  "developer": "CSM",
  "publisher": "W.T.B.",
  "release_date": "Mar 12, 2018",
  "price_usd": 4.99,
  "genres": [
    "Action",
    "Adventure",
    "Indie",
    "RPG"
  ],
  "tags": [
    "Action",
    "Adventure",
    "Indie",
    "RPG"
  ],
  "platforms": [
    "windows"
  ],
  "short_description": "I'm a Simple Man. I See Boobs I Upvote.",
  "header_image_url": "https://shared.akamai.steamstatic.com/store_item_assets/steam/apps/794300/header.jpg?t=1561709268",
  "screenshots": [
    "https://shared.akamai.steamstatic.com/store_item_assets/steam/apps/794300/ss_b4ac0dbf8ffb561dcf211b62b07690b25c91f520.600x338.jpg?t=1561709268",
    "https://shared.akamai.steamstatic.com/store_item_assets/steam/apps/794300/ss_2a83ed3e4eb577677a6b1a1a681a06d89b0c5aef.600x338.jpg?t=1561709268",
    "https://shared.akamai.steamstatic.com/store_item_assets/steam/apps/794300/ss_d8d969a95c05db695fa97a96238d262767a28e01.600x338.jpg?t=1561709268",
    "https://shared.akamai.steamstatic.com/store_item_assets/steam/apps/794300/ss_f7542b8f85478ebf2613c705d2dc9c9b6a89b2f1.600x338.jpg?t=1561709268",
    "https://shared.akamai.steamstatic.com/store_item_assets/steam/apps/794300/ss_dba7072756cf79d2d0ad460b01ccca64a5b10399.600x338.jpg?t=1561709268",
    "https://shared.akamai.steamstatic.com/store_item_assets/steam/apps/794300/ss_30d1dc53ea24366f2f8238b0250461be3adbf449.600x338.jpg?t=1561709268"
  ],
  "detailed_description": "When a simple man goes on a trip, he is interested in 2 things: national costumes and girls.<br />\r\n<br />\r\nWe go on a round-the-world trip and visit 10 countries: China, Germany, Brazil, France, Italy, Russia, USA, Great Britain, Canada and Japan.<br />\r\nThere we will enjoy all the delights of this country and appreciate them.<br />\r\n<br />\r\nWe will also be able to attend the parade dedicated to supporting the LGBT movement and there we will support all those present.<br />\r\n<br />\r\nDo you like to put likes? And if also beautiful girls? And not very beautiful, too? This game is specially for you!<br />\r\n<br />\r\nFly in different countries, put likes for different girls  (and not only), dodge the hate (dislikes) and go through the endless level.<br />\r\n<br />\r\nFeatures:<br />\r\n<br />\r\n- You travel the world and vote for female dignity.<br />\r\n<br />\r\n- Interesting story;<br />\r\n<br />\r\n- A simple gameplay;<br />\r\n<br />\r\n- Easy to master;<br />\r\n<br />\r\n- A lot of good humor;<br />\r\n<br />\r\n- Music is created with the help of AI;<br />\r\n<br />\r\n- Steam Achievements.<br />\r\n<br />\r\nI'm a simple man. I see this game - I'm buying.",
  "about_the_game": "When a simple man goes on a trip, he is interested in 2 things: national costumes and girls.<br />\r\n<br />\r\nWe go on a round-the-world trip and visit 10 countries: China, Germany, Brazil, France, Italy, Russia, USA, Great Britain, Canada and Japan.<br />\r\nThere we will enjoy all the delights of this country and appreciate them.<br />\r\n<br />\r\nWe will also be able to attend the parade dedicated to supporting the LGBT movement and there we will support all those present.<br />\r\n<br />\r\nDo you like to put likes? And if also beautiful girls? And not very beautiful, too? This game is specially for you!<br />\r\n<br />\r\nFly in different countries, put likes for different girls  (and not only), dodge the hate (dislikes) and go through the endless level.<br />\r\n<br />\r\nFeatures:<br />\r\n<br />\r\n- You travel the world and vote for female dignity.<br />\r\n<br />\r\n- Interesting story;<br />\r\n<br />\r\n- A simple gameplay;<br />\r\n<br />\r\n- Easy to master;<br />\r\n<br />\r\n- A lot of good humor;<br />\r\n<br />\r\n- Music is created with the help of AI;<br />\r\n<br />\r\n- Steam Achievements.<br />\r\n<br />\r\nI'm a simple man. I see this game - I'm buying.",
  "supported_languages": "English, Russian",
  "metacritic_score": null,
  "metacritic_url": "",
  "categories": [
    "Single-player",
    "Steam Achievements",
    "Family Sharing"
  ],
  "trailer_url": "",
  "total_recommendations": 0,
  "rising_score": 0.0,
  "gem_score": 0.0,
  "hype_score": 0.0,
  "review_velocity_7d": 0.0,
  "follower_velocity_7d": 0.0,
  "classification": "tracked",
  "review_count": 29,
  "review_positive": 13,
  "review_percentage": 44.8,
  "owner_estimate": 0,
  "ccu_estimate": 0,
  "follower_count": 0,
  "median_playtime_minutes": 0,
  "history": [
    {
      "date": "2026-03-21",
      "review_count": 30,
      "review_percentage": 43.3,
      "ccu_estimate": 0,
      "follower_count": 0
    },
    {
      "date": "2026-03-23",
      "review_count": 29,
      "review_percentage": 44.8,
      "ccu_estimate": 0,
      "follower_count": 0
    }
  ],
  "reviews": []
}