{
  "steam_app_id": 213610,
  "name": "Sonic Adventure 2",
  "slug": "sonic-adventure-2",
  "developer": "SEGA",
  "publisher": "",
  "release_date": "2012-11-19",
  "price_usd": 4.99,
  "genres": [
    "Action"
  ],
  "tags": [
    "Action"
  ],
  "platforms": [
    "windows"
  ],
  "short_description": "Experience two unique adventures featuring both long-time heroes and new and returning villains as they battle for the fate of the world!",
  "header_image_url": "https://shared.akamai.steamstatic.com/store_item_assets/steam/apps/213610/header.jpg?t=1762751748",
  "screenshots": [],
  "rising_score": 0.0038,
  "gem_score": 0.0,
  "hype_score": 0.0,
  "review_velocity_7d": 1375.3000000000002,
  "follower_velocity_7d": 0.0,
  "classification": "tracked",
  "review_count": 27506,
  "review_positive": 0,
  "review_percentage": 89.3,
  "owner_estimate": 1500000,
  "ccu_estimate": 0,
  "follower_count": 0,
  "median_playtime_minutes": 0,
  "history": [
    {
      "date": "2026-04-04",
      "review_count": 27506,
      "review_percentage": 89.3,
      "ccu_estimate": 0,
      "follower_count": 0
    }
  ]
}