{
  "steam_app_id": 1228450,
  "name": "Speed And Survive Ball, 速度与幸存之球",
  "slug": "speed-and-survive-ball-速度与幸存之球",
  "developer": "YTLX 工作室",
  "publisher": "YTLX工作室",
  "release_date": "Feb 11, 2020",
  "price_usd": 0.99,
  "genres": [
    "Action",
    "Casual",
    "Indie",
    "Racing"
  ],
  "tags": [
    "Action",
    "Casual",
    "Indie",
    "Racing"
  ],
  "platforms": [
    "windows"
  ],
  "short_description": "come together , Look at your global ranking!（Version new function: leaderboard）",
  "header_image_url": "https://shared.akamai.steamstatic.com/store_item_assets/steam/apps/1228450/header.jpg?t=1587343799",
  "screenshots": [
    "https://shared.akamai.steamstatic.com/store_item_assets/steam/apps/1228450/ss_96547f16e17379a68961998f06f837b568e30ee5.600x338.jpg?t=1587343799",
    "https://shared.akamai.steamstatic.com/store_item_assets/steam/apps/1228450/ss_f1484df491ac5f48874497eb5ca090c7c9d61662.600x338.jpg?t=1587343799",
    "https://shared.akamai.steamstatic.com/store_item_assets/steam/apps/1228450/ss_ab2aeceb6c497b384b2c892c2c6db59a2c99b425.600x338.jpg?t=1587343799",
    "https://shared.akamai.steamstatic.com/store_item_assets/steam/apps/1228450/ss_e1c4ede74a22da40c60a476177d5e3868f475551.600x338.jpg?t=1587343799",
    "https://shared.akamai.steamstatic.com/store_item_assets/steam/apps/1228450/ss_f0bce07f4c6d89d8d6988177bd83d2ed31137d73.600x338.jpg?t=1587343799",
    "https://shared.akamai.steamstatic.com/store_item_assets/steam/apps/1228450/ss_4b19ffc6f455eb9c28c1c14435ba203ce67bc9de.600x338.jpg?t=1587343799",
    "https://shared.akamai.steamstatic.com/store_item_assets/steam/apps/1228450/ss_fb1cd63b5a745fa59a89e1b144549f2a6cf40df8.600x338.jpg?t=1587343799",
    "https://shared.akamai.steamstatic.com/store_item_assets/steam/apps/1228450/ss_2a75fd2c0fbd0d8afa823482fb937ea7e90afb60.600x338.jpg?t=1587343799"
  ],
  "detailed_description": "<strong><h2 class=\"bb_tag\" >What kind of work is this?</h2></strong><br>You help a small ball to avoid the game of deadly squares from around. The small ball needs speed to survive. Please help it.<br><br><strong><h2 class=\"bb_tag\" >Control method:</h2></strong><br>Up, down, left and right, enter, ESC<br><br><strong><h2 class=\"bb_tag\" >Characteristic:</h2></strong><br>1. This is a game that takes only a short time for each game.<br>2. It's a game that tests concentration.<br>3. This is a small ball running to survive.<br>4. This is an action game to test and strengthen your emergency response.<br>5. It's a game with a little bit of strategy. <br><br>This is a 2-person small team product. I hope you can like it and put forward suggestions for improvement. If you can add it in the next version.<br><br><strong><h2 class=\"bb_tag\" >Update:</h2></strong><br>Update: March 3, 2020<br>　　　　UI optimization, from text to pictures, add a little expressiveness and beauty!<br><br>Update:March 31, 2020<br>　　　　add other platforms,<br>　　　　Google Play :  name \"SpeedAndSurvive\"<br>　　　　　　()<br>　　　　Ios : name \"Speed And Survive Ball,速度与幸存之球\"<br>Update:April 4, 2020<br>　　　　Add  leaderboard",
  "about_the_game": "<strong><h2 class=\"bb_tag\" >What kind of work is this?</h2></strong><br>You help a small ball to avoid the game of deadly squares from around. The small ball needs speed to survive. Please help it.<br><br><strong><h2 class=\"bb_tag\" >Control method:</h2></strong><br>Up, down, left and right, enter, ESC<br><br><strong><h2 class=\"bb_tag\" >Characteristic:</h2></strong><br>1. This is a game that takes only a short time for each game.<br>2. It's a game that tests concentration.<br>3. This is a small ball running to survive.<br>4. This is an action game to test and strengthen your emergency response.<br>5. It's a game with a little bit of strategy. <br><br>This is a 2-person small team product. I hope you can like it and put forward suggestions for improvement. If you can add it in the next version.<br><br><strong><h2 class=\"bb_tag\" >Update:</h2></strong><br>Update: March 3, 2020<br>　　　　UI optimization, from text to pictures, add a little expressiveness and beauty!<br><br>Update:March 31, 2020<br>　　　　add other platforms,<br>　　　　Google Play :  name \"SpeedAndSurvive\"<br>　　　　　　()<br>　　　　Ios : name \"Speed And Survive Ball,速度与幸存之球\"<br>Update:April 4, 2020<br>　　　　Add  leaderboard",
  "supported_languages": "English<strong>*</strong>, Simplified Chinese<strong>*</strong><br><strong>*</strong>languages with full audio support",
  "metacritic_score": null,
  "metacritic_url": "",
  "categories": [
    "Single-player",
    "Family Sharing"
  ],
  "trailer_url": "",
  "total_recommendations": 0,
  "rising_score": 0.0,
  "gem_score": 0.0,
  "hype_score": 0.0,
  "review_velocity_7d": 0.0,
  "follower_velocity_7d": 0.0,
  "classification": "tracked",
  "review_count": 1,
  "review_positive": 1,
  "review_percentage": 100.0,
  "owner_estimate": 0,
  "ccu_estimate": 0,
  "follower_count": 0,
  "median_playtime_minutes": 0,
  "history": [
    {
      "date": "2026-03-21",
      "review_count": 1,
      "review_percentage": 100.0,
      "ccu_estimate": 0,
      "follower_count": 0
    },
    {
      "date": "2026-03-24",
      "review_count": 1,
      "review_percentage": 100.0,
      "ccu_estimate": 0,
      "follower_count": 0
    }
  ],
  "reviews": []
}