{
  "steam_app_id": 2540820,
  "name": "Starfend",
  "slug": "starfend",
  "developer": "Ranieri Silva, Piercarlo Silva",
  "publisher": "",
  "release_date": "2023-12-14",
  "price_usd": 1.04,
  "genres": [
    "Action",
    "Casual",
    "Indie",
    "Strategy"
  ],
  "tags": [
    "Action",
    "Casual",
    "Indie",
    "Strategy"
  ],
  "platforms": [
    "windows",
    "mac",
    "linux"
  ],
  "short_description": "Place defenses strategically, upgrade and combine them. Protect planet orbits with your fleet. Face hordes of meteors in endless 3D levels. Compete on the global leaderboard! Can you make it to the to",
  "header_image_url": "https://shared.akamai.steamstatic.com/store_item_assets/steam/apps/2540820/f49656cf21417934fc16e1e949d74fc40d769004/header.jpg?t=1764529829",
  "screenshots": [],
  "review_count": 12,
  "review_positive": 0,
  "review_percentage": 91.7,
  "owner_estimate": 0,
  "ccu_estimate": 0,
  "follower_count": 0,
  "median_playtime_minutes": 0,
  "history": [
    {
      "date": "2026-04-04",
      "review_count": 12,
      "review_percentage": 91.7,
      "ccu_estimate": 0,
      "follower_count": 0
    }
  ]
}