{
  "steam_app_id": 2790820,
  "name": "Sukfaristo",
  "slug": "sukfaristo",
  "developer": "Bloub Team, Concepts",
  "publisher": "",
  "release_date": "2024-02-08",
  "price_usd": 1.39,
  "genres": [
    "Casual",
    "Indie",
    "Early Access"
  ],
  "tags": [
    "Casual",
    "Indie",
    "Early Access"
  ],
  "platforms": [
    "windows"
  ],
  "short_description": "Discover Sukfaristo, a captivating puzzle game where you combine animals to harvest their precious juice. With unique physics-based gameplay and stimulating challenges, dive into a cute and addictive ",
  "header_image_url": "https://shared.akamai.steamstatic.com/store_item_assets/steam/apps/2790820/header.jpg?t=1715295204",
  "screenshots": [],
  "review_count": 4,
  "review_positive": 0,
  "review_percentage": 100.0,
  "owner_estimate": 0,
  "ccu_estimate": 0,
  "follower_count": 0,
  "median_playtime_minutes": 0,
  "history": [
    {
      "date": "2026-04-04",
      "review_count": 4,
      "review_percentage": 100.0,
      "ccu_estimate": 0,
      "follower_count": 0
    }
  ]
}