{
  "steam_app_id": 2223820,
  "name": "Supermarket Times",
  "slug": "supermarket-times",
  "developer": "Rabbit Hole Games",
  "publisher": "",
  "release_date": "2024-02-14",
  "price_usd": 2.99,
  "genres": [
    "Casual",
    "Indie",
    "Simulation"
  ],
  "tags": [
    "Casual",
    "Indie",
    "Simulation"
  ],
  "platforms": [
    "windows"
  ],
  "short_description": "Prepare to enter the supermarket! Supermarket Times is a surreal comedy point-and-click shopping simulator. Complete legendary supermarket tasks: buy alcohol for the teenagers, stamp on the rat, and h",
  "header_image_url": "https://shared.akamai.steamstatic.com/store_item_assets/steam/apps/2223820/378c50d2c3e99df2b7a8cd5c26851facb229b9b6/header.jpg?t=1752233690",
  "screenshots": [],
  "rising_score": 0.0,
  "gem_score": 0.0,
  "hype_score": 0.0,
  "review_velocity_7d": 2.0500000000000003,
  "follower_velocity_7d": 0.0,
  "classification": "tracked",
  "review_count": 41,
  "review_positive": 0,
  "review_percentage": 92.7,
  "owner_estimate": 0,
  "ccu_estimate": 0,
  "follower_count": 0,
  "median_playtime_minutes": 0,
  "history": [
    {
      "date": "2026-04-04",
      "review_count": 41,
      "review_percentage": 92.7,
      "ccu_estimate": 0,
      "follower_count": 0
    }
  ]
}