{
  "steam_app_id": 250500,
  "name": "Super Amazing Wagon Adventure",
  "slug": "super-amazing-wagon-adventure",
  "developer": "sparsevector",
  "publisher": "",
  "release_date": "2013-10-17",
  "price_usd": 1.01,
  "genres": [
    "Action",
    "Adventure",
    "Indie"
  ],
  "tags": [
    "Action",
    "Adventure",
    "Indie"
  ],
  "platforms": [
    "windows"
  ],
  "short_description": "Super Amazing Wagon Adventure is a fast-paced 2d shooting game with a random story. You control a group of three migrants traveling west along a wagon trail. The game consists of short scenes that are sequenced together in a semi-random way to tell a crazy adventure story.",
  "header_image_url": "https://shared.akamai.steamstatic.com/store_item_assets/steam/apps/250500/header.jpg?t=1742839859",
  "screenshots": [],
  "rising_score": 0.0003,
  "gem_score": 0.0,
  "hype_score": 0.0,
  "review_velocity_7d": 96.2,
  "follower_velocity_7d": 0.0,
  "classification": "tracked",
  "review_count": 1924,
  "review_positive": 0,
  "review_percentage": 95.3,
  "owner_estimate": 0,
  "ccu_estimate": 0,
  "follower_count": 0,
  "median_playtime_minutes": 0,
  "history": [
    {
      "date": "2026-04-04",
      "review_count": 1924,
      "review_percentage": 95.3,
      "ccu_estimate": 0,
      "follower_count": 0
    }
  ]
}