{
  "steam_app_id": 1655060,
  "name": "Switch It",
  "slug": "switch-it",
  "developer": "Lucas Fernandez",
  "publisher": "Lucas Fernandez",
  "release_date": "Jun 17, 2021",
  "price_usd": 0.99,
  "genres": [
    "Casual",
    "Indie"
  ],
  "tags": [
    "Casual",
    "Indie"
  ],
  "platforms": [
    "windows"
  ],
  "short_description": "A bit frustrating game where you have to reach the end using the different types of blocks that you have.",
  "header_image_url": "https://shared.akamai.steamstatic.com/store_item_assets/steam/apps/1655060/header.jpg?t=1672955382",
  "screenshots": [
    "https://shared.akamai.steamstatic.com/store_item_assets/steam/apps/1655060/ss_a63aef681b23489c414e196daef73177bda0e80e.600x338.jpg?t=1672955382",
    "https://shared.akamai.steamstatic.com/store_item_assets/steam/apps/1655060/ss_5d00d575b1a644f271039ffa5bdff0dcc77ee460.600x338.jpg?t=1672955382",
    "https://shared.akamai.steamstatic.com/store_item_assets/steam/apps/1655060/ss_c5db7a3455bf8664a53f519e56e82cfdbbefaeac.600x338.jpg?t=1672955382",
    "https://shared.akamai.steamstatic.com/store_item_assets/steam/apps/1655060/ss_c5b1946d65691b3aa03db86d912f145f56f90154.600x338.jpg?t=1672955382",
    "https://shared.akamai.steamstatic.com/store_item_assets/steam/apps/1655060/ss_f96bebdb171d20f9d586e77151f8a8d6bf07619c.600x338.jpg?t=1672955382"
  ],
  "detailed_description": "A bit frustrating game where you have to reach the end using the different types of blocks that you have.<br />\r\n<br />\r\n<br />\r\n-You have unlimited attempts to complete the game.<br />\r\n<br />\r\n-You can't save game.<br />\r\n<br />\r\n-Use the checkpoints so you don't have to start from the beginning.<br />\r\n<br />\r\n-Use the different blocks wisely.<br />\r\n<br />\r\n-Go to the end without crying.",
  "about_the_game": "A bit frustrating game where you have to reach the end using the different types of blocks that you have.<br />\r\n<br />\r\n<br />\r\n-You have unlimited attempts to complete the game.<br />\r\n<br />\r\n-You can't save game.<br />\r\n<br />\r\n-Use the checkpoints so you don't have to start from the beginning.<br />\r\n<br />\r\n-Use the different blocks wisely.<br />\r\n<br />\r\n-Go to the end without crying.",
  "supported_languages": "English",
  "metacritic_score": null,
  "metacritic_url": "",
  "categories": [
    "Single-player",
    "Family Sharing"
  ],
  "trailer_url": "",
  "total_recommendations": 0,
  "rising_score": 0.0,
  "gem_score": 0.0,
  "hype_score": 0.0,
  "review_velocity_7d": 0.0,
  "follower_velocity_7d": 0.0,
  "classification": "tracked",
  "review_count": 2,
  "review_positive": 2,
  "review_percentage": 100.0,
  "owner_estimate": 0,
  "ccu_estimate": 0,
  "follower_count": 0,
  "median_playtime_minutes": 0,
  "history": [
    {
      "date": "2026-03-21",
      "review_count": 2,
      "review_percentage": 100.0,
      "ccu_estimate": 0,
      "follower_count": 0
    },
    {
      "date": "2026-03-24",
      "review_count": 2,
      "review_percentage": 100.0,
      "ccu_estimate": 0,
      "follower_count": 0
    }
  ],
  "reviews": []
}