{
  "steam_app_id": 3431040,
  "name": "That's not my Neighbor",
  "slug": "thats-not-my-neighbor",
  "developer": "Nachosama Games",
  "publisher": "",
  "release_date": "2025-03-11",
  "price_usd": 2.99,
  "genres": [
    "Adventure",
    "Casual",
    "Indie",
    "Simulation"
  ],
  "tags": [
    "Adventure",
    "Casual",
    "Indie",
    "Simulation"
  ],
  "platforms": [
    "windows",
    "linux"
  ],
  "short_description": "It's 1955, and for unknown reasons, doppelgangers are more common than usual. Therefore, the Department of Doppelganger Detection (D.D.D.) has taken action. You are the doorman of an apartment complex",
  "header_image_url": "https://shared.akamai.steamstatic.com/store_item_assets/steam/apps/3431040/header.jpg?t=1763509556",
  "screenshots": [],
  "rising_score": 0.0006,
  "gem_score": 0.0,
  "hype_score": 0.0,
  "review_velocity_7d": 209.5,
  "follower_velocity_7d": 0.0,
  "classification": "tracked",
  "review_count": 4190,
  "review_positive": 0,
  "review_percentage": 88.6,
  "owner_estimate": 150000,
  "ccu_estimate": 0,
  "follower_count": 0,
  "median_playtime_minutes": 0,
  "history": [
    {
      "date": "2026-04-04",
      "review_count": 4190,
      "review_percentage": 88.6,
      "ccu_estimate": 0,
      "follower_count": 0
    }
  ]
}