{
  "steam_app_id": 955290,
  "name": "The Blood Eclipse",
  "slug": "the-blood-eclipse",
  "developer": "Only Human Studios",
  "publisher": "",
  "release_date": "2018-10-20",
  "price_usd": 3.99,
  "genres": [
    "Action",
    "Adventure",
    "Indie"
  ],
  "tags": [
    "Action",
    "Adventure",
    "Indie"
  ],
  "platforms": [
    "windows",
    "mac",
    "linux"
  ],
  "short_description": "The longest lunar eclipse in each century shall bear the stain of blood -- both in the sky and on the ground. Try to survive in this humans vs zombies multiplayer game!",
  "header_image_url": "https://shared.akamai.steamstatic.com/store_item_assets/steam/apps/955290/header.jpg?t=1549404982",
  "screenshots": [],
  "rising_score": 0.0,
  "gem_score": 0.0,
  "hype_score": 0.0,
  "review_velocity_7d": 0.2,
  "follower_velocity_7d": 0.0,
  "classification": "tracked",
  "review_count": 4,
  "review_positive": 0,
  "review_percentage": 0.0,
  "owner_estimate": 0,
  "ccu_estimate": 0,
  "follower_count": 0,
  "median_playtime_minutes": 0,
  "history": [
    {
      "date": "2026-04-04",
      "review_count": 4,
      "review_percentage": 0.0,
      "ccu_estimate": 0,
      "follower_count": 0
    }
  ]
}