{
  "steam_app_id": 1180360,
  "name": "Two Love",
  "slug": "two-love",
  "developer": "Reporter Zero",
  "publisher": "Reporter Zero",
  "release_date": "Jan 25, 2020",
  "price_usd": 0.0,
  "genres": [
    "Adventure",
    "Free To Play"
  ],
  "tags": [
    "Adventure",
    "Free To Play"
  ],
  "platforms": [
    "windows"
  ],
  "short_description": "文字冒险 英格兰贵族洛各斯·因瑟恩再也忍受不了疾病的折磨，正当他决定自主了断生命时，遇到了一名黑发红瞳的旅人······吸血鬼安克里蒂·沃该依然在寻觅她想要的，在坎维岛上，她见到了一丝可能性······塔莉亚特·阿道尔追寻着她的仇人，一则消息传来······来自东方的杀手欧瑞特见证着。",
  "header_image_url": "https://shared.akamai.steamstatic.com/store_item_assets/steam/apps/1180360/header.jpg?t=1764242114",
  "screenshots": [
    "https://shared.akamai.steamstatic.com/store_item_assets/steam/apps/1180360/ss_0522bb21d3669313afe65d64c7c6455c69bcbb44.600x338.jpg?t=1764242114",
    "https://shared.akamai.steamstatic.com/store_item_assets/steam/apps/1180360/ss_f8f73714a2f462998c73aad84a6042e3427e244d.600x338.jpg?t=1764242114",
    "https://shared.akamai.steamstatic.com/store_item_assets/steam/apps/1180360/ss_a1bdda48097ee5d13015d52afd5041f6171000fa.600x338.jpg?t=1764242114",
    "https://shared.akamai.steamstatic.com/store_item_assets/steam/apps/1180360/ss_f7166f33320309754409ce29239d41847cde6f47.600x338.jpg?t=1764242114",
    "https://shared.akamai.steamstatic.com/store_item_assets/steam/apps/1180360/ss_a2297a1463322b1302b057033f43c693cb01a79c.600x338.jpg?t=1764242114"
  ],
  "detailed_description": "1698年，舞台为英国，幻想性的故事。<br />\r\n<br />\r\n英格兰贵族洛各斯·因瑟恩再也忍受不了疾病的折磨，正当他决定自主了断生命时，遇到了一名黑发红瞳的旅人······<br />\r\n吸血鬼安克里蒂·沃该依然在寻觅她想要的，在坎维岛上，她见到了一丝可能性······<br />\r\n塔莉亚特·阿道尔追寻着她的仇人，一则消息传来······<br />\r\n来自东方的杀手欧瑞特见证着。<br />\r\n<br />\r\n彻头彻尾的第一人称。<br />\r\n多分支，多结局。<br />\r\n古典画作，英国风景画与俄国风景画。<br />\r\n古典音乐，巴赫、舒伯特、李斯特······",
  "about_the_game": "1698年，舞台为英国，幻想性的故事。<br />\r\n<br />\r\n英格兰贵族洛各斯·因瑟恩再也忍受不了疾病的折磨，正当他决定自主了断生命时，遇到了一名黑发红瞳的旅人······<br />\r\n吸血鬼安克里蒂·沃该依然在寻觅她想要的，在坎维岛上，她见到了一丝可能性······<br />\r\n塔莉亚特·阿道尔追寻着她的仇人，一则消息传来······<br />\r\n来自东方的杀手欧瑞特见证着。<br />\r\n<br />\r\n彻头彻尾的第一人称。<br />\r\n多分支，多结局。<br />\r\n古典画作，英国风景画与俄国风景画。<br />\r\n古典音乐，巴赫、舒伯特、李斯特······",
  "supported_languages": "Simplified Chinese",
  "metacritic_score": null,
  "metacritic_url": "",
  "categories": [
    "Single-player",
    "Steam Cloud"
  ],
  "trailer_url": "",
  "total_recommendations": 0,
  "rising_score": 0.0,
  "gem_score": 0.0,
  "hype_score": 0.0,
  "review_velocity_7d": 0.0,
  "follower_velocity_7d": 0.0,
  "classification": "new_release",
  "review_count": 10,
  "review_positive": 10,
  "review_percentage": 100.0,
  "owner_estimate": 0,
  "ccu_estimate": 0,
  "follower_count": 0,
  "median_playtime_minutes": 0,
  "history": [
    {
      "date": "2026-03-21",
      "review_count": 10,
      "review_percentage": 90.0,
      "ccu_estimate": 0,
      "follower_count": 0
    },
    {
      "date": "2026-03-24",
      "review_count": 10,
      "review_percentage": 100.0,
      "ccu_estimate": 0,
      "follower_count": 0
    }
  ],
  "reviews": []
}