{
  "steam_app_id": 2060590,
  "name": "Wilmot Works It Out",
  "slug": "wilmot-works-it-out",
  "developer": "Hollow Ponds, Richard Hogg, Talha Kaya",
  "publisher": "",
  "release_date": "2024-10-23",
  "price_usd": 10.49,
  "genres": [
    "Casual",
    "Indie"
  ],
  "tags": [
    "Casual",
    "Indie"
  ],
  "platforms": [
    "windows",
    "mac"
  ],
  "short_description": "Wilmot Works It Out is a puzzle building game about completing beautiful images and using them to decorate the walls of your house.",
  "header_image_url": "https://shared.akamai.steamstatic.com/store_item_assets/steam/apps/2060590/header.jpg?t=1762885861",
  "screenshots": [],
  "rising_score": 0.0019,
  "gem_score": 0.4352,
  "hype_score": 0.0,
  "review_velocity_7d": 0.0,
  "follower_velocity_7d": 0.0,
  "classification": "new_release",
  "review_count": 750,
  "review_positive": 0,
  "review_percentage": 98.0,
  "owner_estimate": 10000,
  "ccu_estimate": 0,
  "follower_count": 0,
  "median_playtime_minutes": 0,
  "history": [
    {
      "date": "2026-04-04",
      "review_count": 750,
      "review_percentage": 98.0,
      "ccu_estimate": 0,
      "follower_count": 0
    }
  ]
}