{
  "steam_app_id": 1757950,
  "name": "回家 - Homeward",
  "slug": "回家-homeward",
  "developer": "CHEERFUL CYAN CO., LTD.",
  "publisher": "",
  "release_date": "2022-02-22",
  "price_usd": 7.99,
  "genres": [
    "Adventure",
    "Casual",
    "Indie"
  ],
  "tags": [
    "Adventure",
    "Casual",
    "Indie"
  ],
  "platforms": [
    "windows",
    "mac"
  ],
  "short_description": "\"回家 - Homeward\" a relaxing puzzle game, Follow a team of Leopard Cat, black bears and monkeys, native to Taiwan, as they lead you on an adventure from the city to the mountains, exploring Ta",
  "header_image_url": "https://shared.akamai.steamstatic.com/store_item_assets/steam/apps/1757950/header.jpg?t=1652942157",
  "screenshots": [],
  "rising_score": 0.0,
  "gem_score": 0.0,
  "hype_score": 0.0,
  "review_velocity_7d": 0.65,
  "follower_velocity_7d": 0.0,
  "classification": "tracked",
  "review_count": 13,
  "review_positive": 0,
  "review_percentage": 92.3,
  "owner_estimate": 0,
  "ccu_estimate": 0,
  "follower_count": 0,
  "median_playtime_minutes": 0,
  "history": [
    {
      "date": "2026-04-04",
      "review_count": 13,
      "review_percentage": 92.3,
      "ccu_estimate": 0,
      "follower_count": 0
    }
  ]
}