{
  "steam_app_id": 2416770,
  "name": "绛河之上 Under Supernova",
  "slug": "绛河之上-under-supernova",
  "developer": "UnderSupernovaGroup",
  "publisher": "",
  "release_date": "2023-05-31",
  "price_usd": 7.99,
  "genres": [
    "Indie",
    "RPG",
    "Simulation",
    "Strategy",
    "Early Access"
  ],
  "tags": [
    "Indie",
    "RPG",
    "Simulation",
    "Strategy",
    "Early Access"
  ],
  "platforms": [
    "windows"
  ],
  "short_description": "An instant strategy science fiction simulation survival sandbox game. Players can control individuals, teams, and manage multiple bases. Players can farm, build, excavate, fight, produce, graze, explo",
  "header_image_url": "https://shared.akamai.steamstatic.com/store_item_assets/steam/apps/2416770/header.jpg?t=1752033895",
  "screenshots": [],
  "rising_score": 0.0,
  "gem_score": 0.0,
  "hype_score": 0.0,
  "review_velocity_7d": 0.5,
  "follower_velocity_7d": 0.0,
  "classification": "tracked",
  "review_count": 10,
  "review_positive": 0,
  "review_percentage": 80.0,
  "owner_estimate": 0,
  "ccu_estimate": 0,
  "follower_count": 0,
  "median_playtime_minutes": 0,
  "history": [
    {
      "date": "2026-04-04",
      "review_count": 10,
      "review_percentage": 80.0,
      "ccu_estimate": 0,
      "follower_count": 0
    }
  ]
}